{
    "users": [
        {
            "email": "joao@joao.com",
            "password": "$2a$10$i5DXc0KFVTCDXWI/Pv3P1.Z3LsYZLdMtHkWja7qhU4ufMNa5qs6vO",
            "age": "20",
            "favoriteGames": ["Fortnite", "Valorant", "Minecraft"],
            "socialMedia": "@joao_borchoski",
            "id": 1,
            "name": "joao"
        },
        {
            "email": "anna@anna.com",
            "password": "$2a$10$y.nBDceslzxMiG8Cif.Pvec35qKxJ742Mz9tml76AJHbkblAS1lya",
            "age": "20",
            "favoriteGames": ["Fortnite", "Valorant", "Minecraft"],
            "socialMedia": "@joao_borchoski",
            "id": 2
        }
    ]
}
